<annotation>
    <filename>20241127-142311.jpg</filename>
    <folder>fake-plants</folder>
    <source>
        <database>fake-plants</database>
        <annotation>custom</annotation>
        <image>custom</image>
    </source>
    <size>
        <width>1280</width>
        <height>720</height>
        <depth>3</depth>
    </size>
    <segmented>0</segmented>
    <object>
        <name>dandelion</name>
        <pose>unspecified</pose>
        <truncated>0</truncated>
        <difficult>0</difficult>
        <bndbox>
            <xmin>1030</xmin>
            <ymin>253</ymin>
            <xmax>1235</xmax>
            <ymax>438</ymax>
        </bndbox>
    </object>
    <object>
        <name>dandelion</name>
        <pose>unspecified</pose>
        <truncated>0</truncated>
        <difficult>0</difficult>
        <bndbox>
            <xmin>671</xmin>
            <ymin>106</ymin>
            <xmax>877</xmax>
            <ymax>250</ymax>
        </bndbox>
    </object>
    <object>
        <name>geranium</name>
        <pose>unspecified</pose>
        <truncated>0</truncated>
        <difficult>0</difficult>
        <bndbox>
            <xmin>387</xmin>
            <ymin>85</ymin>
            <xmax>519</xmax>
            <ymax>257</ymax>
        </bndbox>
    </object>
    <object>
        <name>rose</name>
        <pose>unspecified</pose>
        <truncated>0</truncated>
        <difficult>0</difficult>
        <bndbox>
            <xmin>91</xmin>
            <ymin>328</ymin>
            <xmax>320</xmax>
            <ymax>527</ymax>
        </bndbox>
    </object>
    <object>
        <name>rose</name>
        <pose>unspecified</pose>
        <truncated>0</truncated>
        <difficult>0</difficult>
        <bndbox>
            <xmin>701</xmin>
            <ymin>328</ymin>
            <xmax>1001</xmax>
            <ymax>567</ymax>
        </bndbox>
    </object>
    <object>
        <name>geranium</name>
        <pose>unspecified</pose>
        <truncated>0</truncated>
        <difficult>0</difficult>
        <bndbox>
            <xmin>365</xmin>
            <ymin>309</ymin>
            <xmax>614</xmax>
            <ymax>541</ymax>
        </bndbox>
    </object>
</annotation>
