<annotation>
    <filename>20241105-133240.jpg</filename>
    <folder>fake-plants</folder>
    <source>
        <database>fake-plants</database>
        <annotation>custom</annotation>
        <image>custom</image>
    </source>
    <size>
        <width>1280</width>
        <height>720</height>
        <depth>3</depth>
    </size>
    <segmented>0</segmented>
    <object>
        <name>dandelion</name>
        <pose>unspecified</pose>
        <truncated>0</truncated>
        <difficult>0</difficult>
        <bndbox>
            <xmin>562</xmin>
            <ymin>197</ymin>
            <xmax>758</xmax>
            <ymax>374</ymax>
        </bndbox>
    </object>
    <object>
        <name>geranium</name>
        <pose>unspecified</pose>
        <truncated>0</truncated>
        <difficult>0</difficult>
        <bndbox>
            <xmin>136</xmin>
            <ymin>139</ymin>
            <xmax>327</xmax>
            <ymax>319</ymax>
        </bndbox>
    </object>
    <object>
        <name>rose</name>
        <pose>unspecified</pose>
        <truncated>0</truncated>
        <difficult>0</difficult>
        <bndbox>
            <xmin>353</xmin>
            <ymin>373</ymin>
            <xmax>561</xmax>
            <ymax>641</ymax>
        </bndbox>
    </object>
    <object>
        <name>rose</name>
        <pose>unspecified</pose>
        <truncated>0</truncated>
        <difficult>0</difficult>
        <bndbox>
            <xmin>3</xmin>
            <ymin>425</ymin>
            <xmax>193</xmax>
            <ymax>692</ymax>
        </bndbox>
    </object>
</annotation>
